{"nodes": [{"id": "c_users_acer_appgym_gym_saga_design_artifacts_profeandres_components_statcard_tsx", "label": "StatCard.tsx", "file_type": "code", "source_file": "C:\\Users\\Acer\\appgym\\Gym-Saga-Design\\artifacts\\profeandres\\components\\StatCard.tsx", "source_location": "L1"}], "edges": [{"source": "c_users_acer_appgym_gym_saga_design_artifacts_profeandres_components_statcard_tsx", "target": "react", "relation": "imports_from", "confidence": "EXTRACTED", "source_file": "C:\\Users\\Acer\\appgym\\Gym-Saga-Design\\artifacts\\profeandres\\components\\StatCard.tsx", "source_location": "L1", "weight": 1.0}, {"source": "c_users_acer_appgym_gym_saga_design_artifacts_profeandres_components_statcard_tsx", "target": "react_native", "relation": "imports_from", "confidence": "EXTRACTED", "source_file": "C:\\Users\\Acer\\appgym\\Gym-Saga-Design\\artifacts\\profeandres\\components\\StatCard.tsx", "source_location": "L2", "weight": 1.0}, {"source": "c_users_acer_appgym_gym_saga_design_artifacts_profeandres_components_statcard_tsx", "target": "vector_icons", "relation": "imports_from", "confidence": "EXTRACTED", "source_file": "C:\\Users\\Acer\\appgym\\Gym-Saga-Design\\artifacts\\profeandres\\components\\StatCard.tsx", "source_location": "L3", "weight": 1.0}, {"source": "c_users_acer_appgym_gym_saga_design_artifacts_profeandres_components_statcard_tsx", "target": "usecolors", "relation": "imports_from", "confidence": "EXTRACTED", "source_file": "C:\\Users\\Acer\\appgym\\Gym-Saga-Design\\artifacts\\profeandres\\components\\StatCard.tsx", "source_location": "L4", "weight": 1.0}], "raw_calls": []}